<?xml version='1.0' encoding='UTF-8' standalone='yes'?>
<tomtom version="5.3.3" release="Sun Feb 7 15:39:52 2021 -0800">
  <model>
    <command_line>tomtom -oc motifs/Fur-2/tomtom -thresh 0.001 -incomplete-scores -png motifs/Fur-2/meme.txt /opt/conda/lib/python3.9/site-packages/pymodulon/data/meme/collectf.meme /opt/conda/lib/python3.9/site-packages/pymodulon/data/meme/dpinteract.meme /opt/conda/lib/python3.9/site-packages/pymodulon/data/meme/prodoric.meme /opt/conda/lib/python3.9/site-packages/pymodulon/data/meme/regtransbase.meme /opt/conda/lib/python3.9/site-packages/pymodulon/data/meme/SwissRegulon_e_coli.meme</command_line>
    <distance_measure value="ed"/>
    <threshold type="qvalue">0.001</threshold>
    <alphabet name="DNA" like="dna">
      <letter id="A" symbol="A" complement="T" name="Adenine" colour="CC0000"/>
      <letter id="C" symbol="C" complement="G" name="Cytosine" colour="0000CC"/>
      <letter id="G" symbol="G" complement="C" name="Guanine" colour="FFB300"/>
      <letter id="T" symbol="T" aliases="U" complement="A" name="Thymine" colour="008000"/>
      <letter id="N" symbol="N" aliases="X." equals="ACGT" name="Any base"/>
      <letter id="V" symbol="V" equals="ACG" name="Not T"/>
      <letter id="H" symbol="H" equals="ACT" name="Not G"/>
      <letter id="D" symbol="D" equals="AGT" name="Not C"/>
      <letter id="B" symbol="B" equals="CGT" name="Not A"/>
      <letter id="M" symbol="M" equals="AC" name="Amino"/>
      <letter id="R" symbol="R" equals="AG" name="Purine"/>
      <letter id="W" symbol="W" equals="AT" name="Weak"/>
      <letter id="S" symbol="S" equals="CG" name="Strong"/>
      <letter id="Y" symbol="Y" equals="CT" name="Pyrimidine"/>
      <letter id="K" symbol="K" equals="GT" name="Keto"/>
    </alphabet>
    <strands>both</strands>
    <background from="--query--" A="0.3425" C="0.1575" G="0.1575" T="0.3425"/>
    <host>1468acf55fcb</host>
    <when>Tue Jul 13 06:31:53 2021</when>
  </model>
  <query_dbs>
    <db source="motifs/Fur-2/meme.txt" name="meme.txt" loaded="3" excluded="0" last_mod_date="Tue Jul 13 05:52:45 2021"/>
  </query_dbs>
  <target_dbs>
    <db source="/opt/conda/lib/python3.9/site-packages/pymodulon/data/meme/collectf.meme" name="collectf" loaded="84" excluded="0" last_mod_date="Thu Jun 24 01:06:56 2021"/>
    <db source="/opt/conda/lib/python3.9/site-packages/pymodulon/data/meme/dpinteract.meme" name="dpinteract" loaded="68" excluded="0" last_mod_date="Thu Jun 24 01:06:56 2021"/>
    <db source="/opt/conda/lib/python3.9/site-packages/pymodulon/data/meme/prodoric.meme" name="prodoric" loaded="201" excluded="0" last_mod_date="Thu Jun 24 01:06:56 2021"/>
    <db source="/opt/conda/lib/python3.9/site-packages/pymodulon/data/meme/regtransbase.meme" name="regtransbase" loaded="141" excluded="0" last_mod_date="Thu Jun 24 01:06:56 2021"/>
    <db source="/opt/conda/lib/python3.9/site-packages/pymodulon/data/meme/SwissRegulon_e_coli.meme" name="SwissRegulon_e_coli" loaded="97" excluded="0" last_mod_date="Thu Jun 24 01:06:56 2021"/>
  </target_dbs>
  <queries>
    <motif db="0" id="AYYTGNATTACCACNASMTGCA" alt="MEME-2" length="22" nsites="17" evalue="6.7e-007">
      <pos A="0.762237" C="0.0594011" G="0.000921055" T="0.177442"/>
      <pos A="0.118962" C="0.410278" G="0.11788" T="0.35288"/>
      <pos A="0.00200292" C="0.351798" G="0.11788" T="0.528319"/>
      <pos A="0.118962" C="0.234839" G="0.0594011" T="0.586798"/>
      <pos A="0.00200292" C="0.000921055" G="0.761155" T="0.235921"/>
      <pos A="0.235921" C="0.293319" G="0.17636" T="0.294401"/>
      <pos A="0.703757" C="0.0594011" G="0.11788" T="0.118962"/>
      <pos A="0.0604829" C="0.17636" G="0.0594011" T="0.703757"/>
      <pos A="0.00200292" C="0.234839" G="0.0594011" T="0.703757"/>
      <pos A="0.645278" C="0.293319" G="0.0594011" T="0.00200292"/>
      <pos A="0.00200292" C="0.585716" G="0.17636" T="0.235921"/>
      <pos A="0.118962" C="0.878114" G="0.000921055" T="0.00200292"/>
      <pos A="0.645278" C="0.0594011" G="0.293319" T="0.00200292"/>
      <pos A="0.177442" C="0.819634" G="0.000921055" T="0.00200292"/>
      <pos A="0.235921" C="0.234839" G="0.293319" T="0.235921"/>
      <pos A="0.879196" C="0.11788" G="0.000921055" T="0.00200292"/>
      <pos A="0.0604829" C="0.527237" G="0.410278" T="0.00200292"/>
      <pos A="0.528319" C="0.293319" G="0.0594011" T="0.118962"/>
      <pos A="0.177442" C="0.000921055" G="0.0594011" T="0.762237"/>
      <pos A="0.00200292" C="0.234839" G="0.644196" T="0.118962"/>
      <pos A="0.00200292" C="0.936593" G="0.000921055" T="0.0604829"/>
      <pos A="0.645278" C="0.0594011" G="0.000921055" T="0.294401"/>
    </motif>
    <motif db="0" id="TTNTWAWTGAKAATBATTATCAWTTA" alt="MEME-1" length="26" nsites="22" evalue="5.8e-045">
      <pos A="0.182545" C="0.181708" G="0.000712671" T="0.635034"/>
      <pos A="0.182545" C="0.000712671" G="0.045962" T="0.77078"/>
      <pos A="0.182545" C="0.181708" G="0.317455" T="0.318292"/>
      <pos A="0.182545" C="0.226957" G="0.0912103" T="0.499287"/>
      <pos A="0.499287" C="0.000712671" G="0.000712671" T="0.499287"/>
      <pos A="0.861278" C="0.045962" G="0.0912103" T="0.00154977"/>
      <pos A="0.318292" C="0.045962" G="0.13646" T="0.499287"/>
      <pos A="0.00154977" C="0.000712671" G="0.000712671" T="0.997025"/>
      <pos A="0.0920474" C="0.000712671" G="0.815192" T="0.0920474"/>
      <pos A="0.951776" C="0.000712671" G="0.045962" T="0.00154977"/>
      <pos A="0.0920474" C="0.000712671" G="0.317455" T="0.589785"/>
      <pos A="0.951776" C="0.000712671" G="0.000712671" T="0.0467991"/>
      <pos A="0.951776" C="0.000712671" G="0.000712671" T="0.0467991"/>
      <pos A="0.0920474" C="0.0912103" G="0.045962" T="0.77078"/>
      <pos A="0.0467991" C="0.407953" G="0.226957" T="0.318292"/>
      <pos A="0.81603" C="0.000712671" G="0.13646" T="0.0467991"/>
      <pos A="0.0467991" C="0.000712671" G="0.000712671" T="0.951776"/>
      <pos A="0.00154977" C="0.000712671" G="0.000712671" T="0.997025"/>
      <pos A="0.81603" C="0.13646" G="0.000712671" T="0.0467991"/>
      <pos A="0.00154977" C="0.000712671" G="0.000712671" T="0.997025"/>
      <pos A="0.00154977" C="0.996188" G="0.000712671" T="0.00154977"/>
      <pos A="0.997025" C="0.000712671" G="0.000712671" T="0.00154977"/>
      <pos A="0.589785" C="0.045962" G="0.000712671" T="0.36354"/>
      <pos A="0.0467991" C="0.000712671" G="0.045962" T="0.906527"/>
      <pos A="0.0920474" C="0.045962" G="0.181708" T="0.680283"/>
      <pos A="0.725532" C="0.000712671" G="0.0912103" T="0.182545"/>
    </motif>
    <motif db="0" id="WGCAAKCGTAWCWABDAGSATT" alt="MEME-3" length="22" nsites="9" evalue="4.1e-004">
      <pos A="0.663105" C="0.00173077" G="0.00173077" T="0.333434"/>
      <pos A="0.00376373" C="0.221511" G="0.770962" T="0.00376373"/>
      <pos A="0.223544" C="0.661072" G="0.111621" T="0.00376373"/>
      <pos A="0.992775" C="0.00173077" G="0.00173077" T="0.00376373"/>
      <pos A="0.772995" C="0.00173077" G="0.111621" T="0.113654"/>
      <pos A="0.113654" C="0.00173077" G="0.441291" T="0.443324"/>
      <pos A="0.00376373" C="0.770962" G="0.00173077" T="0.223544"/>
      <pos A="0.223544" C="0.00173077" G="0.770962" T="0.00376373"/>
      <pos A="0.00376373" C="0.221511" G="0.111621" T="0.663105"/>
      <pos A="0.992775" C="0.00173077" G="0.00173077" T="0.00376373"/>
      <pos A="0.663105" C="0.00173077" G="0.00173077" T="0.333434"/>
      <pos A="0.223544" C="0.770962" G="0.00173077" T="0.00376373"/>
      <pos A="0.663105" C="0.00173077" G="0.00173077" T="0.333434"/>
      <pos A="0.772995" C="0.00173077" G="0.221511" T="0.00376373"/>
      <pos A="0.00376373" C="0.221511" G="0.441291" T="0.333434"/>
      <pos A="0.333434" C="0.00173077" G="0.331401" T="0.333434"/>
      <pos A="0.772995" C="0.00173077" G="0.111621" T="0.113654"/>
      <pos A="0.00376373" C="0.221511" G="0.770962" T="0.00376373"/>
      <pos A="0.00376373" C="0.331401" G="0.661072" T="0.00376373"/>
      <pos A="0.992775" C="0.00173077" G="0.00173077" T="0.00376373"/>
      <pos A="0.00376373" C="0.00173077" G="0.00173077" T="0.992775"/>
      <pos A="0.113654" C="0.00173077" G="0.00173077" T="0.882885"/>
    </motif>
  </queries>
  <targets>
    <motif db="0" id="EXPREG_00000340" alt="Fur_H.pylori" length="48" nsites="23"
        url="http://www.collectf.org/EXPREG_00000340">
      <pos A="0.434384" C="0.0439716" G="0.0439716" T="0.477673"/>
      <pos A="0.131353" C="0.130552" G="0.347002" T="0.391093"/>
      <pos A="0.304513" C="0.217132" G="0.130552" T="0.347803"/>
      <pos A="0.477673" C="0.0872624" G="0.0872624" T="0.347803"/>
      <pos A="0.261223" C="0.260423" G="0.0872624" T="0.391093"/>
      <pos A="0.564253" C="0.000681821" G="0.0872624" T="0.347803"/>
      <pos A="0.261223" C="0.173842" G="0.130552" T="0.434384"/>
      <pos A="0.391093" C="0.0872624" G="0.000681821" T="0.520963"/>
      <pos A="0.564253" C="0.0872624" G="0.000681821" T="0.347803"/>
      <pos A="0.0880632" C="0.0872624" G="0.0439716" T="0.780704"/>
      <pos A="0.607544" C="0.0872624" G="0.303712" T="0.00148268"/>
      <pos A="0.867283" C="0.000681821" G="0.000681821" T="0.131353"/>
      <pos A="0.261223" C="0.000681821" G="0.000681821" T="0.737413"/>
      <pos A="0.650833" C="0.000681821" G="0.000681821" T="0.347803"/>
      <pos A="0.823994" C="0.0872624" G="0.0439716" T="0.0447725"/>
      <pos A="0.0447725" C="0.0872624" G="0.130552" T="0.737413"/>
      <pos A="0.217933" C="0.433583" G="0.000681821" T="0.347803"/>
      <pos A="0.823994" C="0.000681821" G="0.0439716" T="0.131353"/>
      <pos A="0.131353" C="0.000681821" G="0.000681821" T="0.867283"/>
      <pos A="0.00148268" C="0.0439716" G="0.130552" T="0.823994"/>
      <pos A="0.520963" C="0.000681821" G="0.000681821" T="0.477673"/>
      <pos A="0.0880632" C="0.000681821" G="0.000681821" T="0.910573"/>
      <pos A="0.0447725" C="0.0872624" G="0.000681821" T="0.867283"/>
      <pos A="0.910573" C="0.000681821" G="0.0872624" T="0.00148268"/>
      <pos A="0.477673" C="0.0872624" G="0.130552" T="0.304513"/>
      <pos A="0.564253" C="0.0439716" G="0.0439716" T="0.347803"/>
      <pos A="0.694123" C="0.000681821" G="0.173842" T="0.131353"/>
      <pos A="0.391093" C="0.260423" G="0.0439716" T="0.304513"/>
      <pos A="0.434384" C="0.0439716" G="0.0439716" T="0.477673"/>
      <pos A="0.477673" C="0.0439716" G="0.130552" T="0.347803"/>
      <pos A="0.434384" C="0.0439716" G="0.303712" T="0.217933"/>
      <pos A="0.304513" C="0.347002" G="0.0439716" T="0.304513"/>
      <pos A="0.391093" C="0.0872624" G="0.130552" T="0.391093"/>
      <pos A="0.261223" C="0.0439716" G="0.260423" T="0.434384"/>
      <pos A="0.304513" C="0.303712" G="0.260423" T="0.131353"/>
      <pos A="0.477673" C="0.0439716" G="0.217132" T="0.261223"/>
      <pos A="0.434384" C="0.0439716" G="0.130552" T="0.391093"/>
      <pos A="0.520963" C="0.0439716" G="0.0439716" T="0.391093"/>
      <pos A="0.347803" C="0.130552" G="0.173842" T="0.347803"/>
      <pos A="0.477673" C="0.0872624" G="0.000681821" T="0.434384"/>
      <pos A="0.477673" C="0.173842" G="0.173842" T="0.174643"/>
      <pos A="0.477673" C="0.130552" G="0.130552" T="0.261223"/>
      <pos A="0.477673" C="0.130552" G="0.0872624" T="0.304513"/>
      <pos A="0.261223" C="0.130552" G="0.217132" T="0.391093"/>
      <pos A="0.174643" C="0.173842" G="0.173842" T="0.477673"/>
      <pos A="0.217933" C="0.0872624" G="0.260423" T="0.434384"/>
      <pos A="0.261223" C="0.173842" G="0.0439716" T="0.520963"/>
      <pos A="0.217933" C="0.0872624" G="0.173842" T="0.520963"/>
    </motif>
    <motif db="0" id="EXPREG_00000360" alt="Fur_A.salmonicida" length="25" nsites="23"
        url="http://www.collectf.org/EXPREG_00000360">
      <pos A="0.391093" C="0.0439716" G="0.390292" T="0.174643"/>
      <pos A="0.261223" C="0.173842" G="0.000681821" T="0.564253"/>
      <pos A="0.217933" C="0.0872624" G="0.0872624" T="0.607544"/>
      <pos A="0.217933" C="0.0872624" G="0.303712" T="0.391093"/>
      <pos A="0.347803" C="0.0439716" G="0.0439716" T="0.564253"/>
      <pos A="0.304513" C="0.0439716" G="0.303712" T="0.347803"/>
      <pos A="0.694123" C="0.000681821" G="0.0439716" T="0.261223"/>
      <pos A="0.867283" C="0.000681821" G="0.000681821" T="0.131353"/>
      <pos A="0.174643" C="0.000681821" G="0.000681821" T="0.823994"/>
      <pos A="0.0880632" C="0.0872624" G="0.736612" T="0.0880632"/>
      <pos A="0.737413" C="0.000681821" G="0.130552" T="0.131353"/>
      <pos A="0.131353" C="0.000681821" G="0.0872624" T="0.780704"/>
      <pos A="0.650833" C="0.000681821" G="0.000681821" T="0.347803"/>
      <pos A="0.737413" C="0.000681821" G="0.000681821" T="0.261223"/>
      <pos A="0.00148268" C="0.260423" G="0.0872624" T="0.650833"/>
      <pos A="0.261223" C="0.000681821" G="0.0872624" T="0.650833"/>
      <pos A="0.867283" C="0.000681821" G="0.130552" T="0.00148268"/>
      <pos A="0.217933" C="0.000681821" G="0.0439716" T="0.737413"/>
      <pos A="0.0880632" C="0.173842" G="0.000681821" T="0.737413"/>
      <pos A="0.477673" C="0.347002" G="0.130552" T="0.0447725"/>
      <pos A="0.304513" C="0.000681821" G="0.130552" T="0.564253"/>
      <pos A="0.174643" C="0.347002" G="0.217132" T="0.261223"/>
      <pos A="0.867283" C="0.0872624" G="0.000681821" T="0.0447725"/>
      <pos A="0.434384" C="0.0439716" G="0.000681821" T="0.520963"/>
      <pos A="0.0447725" C="0.0439716" G="0.0872624" T="0.823994"/>
    </motif>
    <motif db="0" id="EXPREG_000007c0" alt="Fur_E.coli" length="31" nsites="26"
        url="http://www.collectf.org/EXPREG_000007c0">
      <pos A="0.384454" C="0.307117" G="0.00060345" T="0.307825"/>
      <pos A="0.576025" C="0.0772317" G="0.115546" T="0.231197"/>
      <pos A="0.192883" C="0.115546" G="0.0772317" T="0.614339"/>
      <pos A="0.0396269" C="0.115546" G="0.268803" T="0.576025"/>
      <pos A="0.422768" C="0.192175" G="0.230488" T="0.154569"/>
      <pos A="0.307825" C="0.0772317" G="0.192175" T="0.422768"/>
      <pos A="0.690968" C="0.00060345" G="0.0389181" T="0.269512"/>
      <pos A="0.690968" C="0.0772317" G="0.0772317" T="0.154569"/>
      <pos A="0.00131226" C="0.115546" G="0.00060345" T="0.882538"/>
      <pos A="0.231197" C="0.0772317" G="0.651944" T="0.0396269"/>
      <pos A="0.844224" C="0.0389181" G="0.0389181" T="0.0779405"/>
      <pos A="0.192883" C="0.00060345" G="0.115546" T="0.690968"/>
      <pos A="0.882538" C="0.00060345" G="0.00060345" T="0.116255"/>
      <pos A="0.652653" C="0.230488" G="0.0772317" T="0.0396269"/>
      <pos A="0.00131226" C="0.115546" G="0.230488" T="0.652653"/>
      <pos A="0.116255" C="0.307117" G="0.15386" T="0.422768"/>
      <pos A="0.844224" C="0.00060345" G="0.115546" T="0.0396269"/>
      <pos A="0.0396269" C="0.00060345" G="0.00060345" T="0.959166"/>
      <pos A="0.00131226" C="0.00060345" G="0.00060345" T="0.997481"/>
      <pos A="0.461082" C="0.230488" G="0.00060345" T="0.307825"/>
      <pos A="0.0396269" C="0.115546" G="0.0772317" T="0.767596"/>
      <pos A="0.00131226" C="0.690259" G="0.00060345" T="0.307825"/>
      <pos A="0.652653" C="0.00060345" G="0.230488" T="0.116255"/>
      <pos A="0.231197" C="0.15386" G="0.00060345" T="0.614339"/>
      <pos A="0.0779405" C="0.115546" G="0.0389181" T="0.767596"/>
      <pos A="0.537711" C="0.115546" G="0.0389181" T="0.307825"/>
      <pos A="0.34614" C="0.15386" G="0.230488" T="0.269512"/>
      <pos A="0.231197" C="0.268803" G="0.0772317" T="0.422768"/>
      <pos A="0.461082" C="0.0389181" G="0.230488" T="0.269512"/>
      <pos A="0.269512" C="0.15386" G="0.15386" T="0.422768"/>
      <pos A="0.192883" C="0.115546" G="0.0772317" T="0.614339"/>
    </motif>
    <motif db="0" id="EXPREG_000008b0" alt="Fur_V.cholerae" length="23" nsites="106"
        url="http://www.collectf.org/EXPREG_000008b0">
      <pos A="0.641227" C="0.0849744" G="0.141524" T="0.132273"/>
      <pos A="0.509277" C="0.00957355" G="0.0849744" T="0.396175"/>
      <pos A="0.0757237" C="0.0378489" G="0.0284238" T="0.858005"/>
      <pos A="0.113424" C="0.0284238" G="0.810705" T="0.0474484"/>
      <pos A="0.810879" C="0.0566991" G="0.0849744" T="0.0474484"/>
      <pos A="0.151124" C="0.0284238" G="0.424276" T="0.396175"/>
      <pos A="0.971105" C="0.00957355" G="0.000148445" T="0.019173"/>
      <pos A="0.773179" C="0.00957355" G="0.0189987" T="0.198249"/>
      <pos A="0.113424" C="0.0661242" G="0.0189987" T="0.801454"/>
      <pos A="0.2925" C="0.235775" G="0.169799" T="0.301925"/>
      <pos A="0.499852" C="0.0566991" G="0.339451" T="0.103999"/>
      <pos A="0.122849" C="0.198075" G="0.0661242" T="0.612953"/>
      <pos A="0.0568735" C="0.0661242" G="0.0661242" T="0.810879"/>
      <pos A="0.518702" C="0.26405" G="0.0284238" T="0.188824"/>
      <pos A="0.0945739" C="0.0284238" G="0.0661242" T="0.810879"/>
      <pos A="0.0474484" C="0.650478" G="0.0378489" T="0.264225"/>
      <pos A="0.876854" C="0.0189987" G="0.0849744" T="0.019173"/>
      <pos A="0.2925" C="0.0378489" G="0.0849744" T="0.584678"/>
      <pos A="0.103999" C="0.0849744" G="0.0755493" T="0.735478"/>
      <pos A="0.245375" C="0.11325" G="0.103825" T="0.537552"/>
      <pos A="0.396175" C="0.122675" G="0.301751" T="0.179399"/>
      <pos A="0.264225" C="0.26405" G="0.198075" T="0.27365"/>
      <pos A="0.452726" C="0.0943995" G="0.216925" T="0.23595"/>
    </motif>
    <motif db="0" id="EXPREG_00000a20" alt="Fur_Y.pestis" length="19" nsites="32"
        url="http://www.collectf.org/EXPREG_00000a20">
      <pos A="0.904494" C="0.0316433" G="0.062796" T="0.00106698"/>
      <pos A="0.468357" C="0.0939486" G="0.125101" T="0.312593"/>
      <pos A="0.00106698" C="0.062796" G="0.0316433" T="0.904494"/>
      <pos A="0.187983" C="0.0316433" G="0.748154" T="0.0322196"/>
      <pos A="0.561815" C="0.156254" G="0.218559" T="0.0633723"/>
      <pos A="0.15683" C="0.0316433" G="0.218559" T="0.592967"/>
      <pos A="0.717578" C="0.000490656" G="0.000490656" T="0.281441"/>
      <pos A="0.811036" C="0.000490656" G="0.0939486" T="0.0945249"/>
      <pos A="0.00106698" C="0.187407" G="0.000490656" T="0.811036"/>
      <pos A="0.125678" C="0.156254" G="0.498933" T="0.219136"/>
      <pos A="0.935646" C="0.0316433" G="0.0316433" T="0.00106698"/>
      <pos A="0.00106698" C="0.000490656" G="0.0316433" T="0.966799"/>
      <pos A="0.0945249" C="0.0316433" G="0.0316433" T="0.842188"/>
      <pos A="0.873341" C="0.000490656" G="0.000490656" T="0.125678"/>
      <pos A="0.00106698" C="0.000490656" G="0.0316433" T="0.966799"/>
      <pos A="0.00106698" C="0.779307" G="0.000490656" T="0.219136"/>
      <pos A="0.935646" C="0.000490656" G="0.062796" T="0.00106698"/>
      <pos A="0.219136" C="0.0316433" G="0.000490656" T="0.748731"/>
      <pos A="0.00106698" C="0.0316433" G="0.0939486" T="0.873341"/>
    </motif>
    <motif db="0" id="EXPREG_00000b40" alt="Fur_B.subtilis" length="22" nsites="24"
        url="http://www.collectf.org/EXPREG_00000b40">
      <pos A="0.250384" C="0.0421476" G="0.457085" T="0.250384"/>
      <pos A="0.540841" C="0.125135" G="0.208122" T="0.125902"/>
      <pos A="0.333371" C="0.125135" G="0.0836407" T="0.457852"/>
      <pos A="0.87279" C="0.000653529" G="0.000653529" T="0.125902"/>
      <pos A="0.623828" C="0.000653529" G="0.000653529" T="0.374865"/>
      <pos A="0.0429153" C="0.0421476" G="0.000653529" T="0.914285"/>
      <pos A="0.00142116" C="0.0421476" G="0.95501" T="0.00142116"/>
      <pos A="0.914285" C="0.000653529" G="0.0421476" T="0.0429153"/>
      <pos A="0.20889" C="0.000653529" G="0.208122" T="0.582334"/>
      <pos A="0.87279" C="0.000653529" G="0.000653529" T="0.125902"/>
      <pos A="0.87279" C="0.0421476" G="0.000653529" T="0.0844084"/>
      <pos A="0.0429153" C="0.0836407" G="0.000653529" T="0.87279"/>
      <pos A="0.00142116" C="0.789036" G="0.000653529" T="0.20889"/>
      <pos A="0.997272" C="0.000653529" G="0.000653529" T="0.00142116"/>
      <pos A="0.0429153" C="0.000653529" G="0.0421476" T="0.914285"/>
      <pos A="0.00142116" C="0.0836407" G="0.000653529" T="0.914285"/>
      <pos A="0.665322" C="0.0836407" G="0.000653529" T="0.250384"/>
      <pos A="0.00142116" C="0.000653529" G="0.0421476" T="0.955778"/>
      <pos A="0.0429153" C="0.95501" G="0.000653529" T="0.00142116"/>
      <pos A="0.955778" C="0.000653529" G="0.0421476" T="0.00142116"/>
      <pos A="0.540841" C="0.0836407" G="0.0421476" T="0.333371"/>
      <pos A="0.0844084" C="0.166629" G="0.000653529" T="0.748309"/>
    </motif>
    <motif db="0" id="EXPREG_00000bc0" alt="PerR_B.subtilis" length="15" nsites="14"
        url="http://www.collectf.org/EXPREG_00000bc0">
      <pos A="0.0733515" C="0.0720394" G="0.00111703" T="0.853493"/>
      <pos A="0.00242907" C="0.0720394" G="0.213883" T="0.711649"/>
      <pos A="0.924414" C="0.00111703" G="0.0720394" T="0.00242907"/>
      <pos A="0.0733515" C="0.00111703" G="0.142961" T="0.782571"/>
      <pos A="0.995337" C="0.00111703" G="0.00111703" T="0.00242907"/>
      <pos A="0.995337" C="0.00111703" G="0.00111703" T="0.00242907"/>
      <pos A="0.0733515" C="0.0720394" G="0.00111703" T="0.853493"/>
      <pos A="0.144273" C="0.00111703" G="0.142961" T="0.711649"/>
      <pos A="0.924414" C="0.00111703" G="0.00111703" T="0.0733515"/>
      <pos A="0.00242907" C="0.00111703" G="0.0720394" T="0.924414"/>
      <pos A="0.0733515" C="0.00111703" G="0.00111703" T="0.924414"/>
      <pos A="0.853493" C="0.00111703" G="0.0720394" T="0.0733515"/>
      <pos A="0.0733515" C="0.00111703" G="0.00111703" T="0.924414"/>
      <pos A="0.782571" C="0.213883" G="0.00111703" T="0.00242907"/>
      <pos A="0.995337" C="0.00111703" G="0.00111703" T="0.00242907"/>
    </motif>
    <motif db="0" id="EXPREG_00000c80" alt="Fur_P.aeruginosa" length="19" nsites="61"
        url="http://www.collectf.org/EXPREG_00000c80">
      <pos A="0.14786" C="0.147557" G="0.573089" T="0.131494"/>
      <pos A="0.409726" C="0.343956" G="0.000257775" T="0.24606"/>
      <pos A="0.14786" C="0.0493573" G="0.360324" T="0.442459"/>
      <pos A="0.867991" C="0.0166239" G="0.0329911" T="0.0823934"/>
      <pos A="0.687959" C="0.0657245" G="0.000257775" T="0.24606"/>
      <pos A="0.0332939" C="0.0166239" G="0.000257775" T="0.949824"/>
      <pos A="0.131494" C="0.0657245" G="0.769489" T="0.0332939"/>
      <pos A="0.818891" C="0.131191" G="0.0493573" T="0.000560556"/>
      <pos A="0.278793" C="0.0493573" G="0.114824" T="0.557025"/>
      <pos A="0.540659" C="0.000257775" G="0.0329911" T="0.426093"/>
      <pos A="0.655225" C="0.294857" G="0.0166239" T="0.0332939"/>
      <pos A="0.0332939" C="0.0984578" G="0.0984578" T="0.769792"/>
      <pos A="0.213327" C="0.540356" G="0.0657245" T="0.180593"/>
      <pos A="0.786158" C="0.0166239" G="0.180291" T="0.0169267"/>
      <pos A="0.180593" C="0.0166239" G="0.000257775" T="0.802525"/>
      <pos A="0.000560556" C="0.0657245" G="0.000257775" T="0.933457"/>
      <pos A="0.507926" C="0.114824" G="0.0820906" T="0.29516"/>
      <pos A="0.000560556" C="0.0984578" G="0.114824" T="0.786158"/>
      <pos A="0.115127" C="0.671289" G="0.0166239" T="0.19696"/>
    </motif>
    <motif db="0" id="EXPREG_000013d0" alt="Fur_L.monocytogenes" length="19" nsites="16"
        url="http://www.collectf.org/EXPREG_000013d0">
      <pos A="0.00212733" C="0.000978264" G="0.994767" T="0.00212733"/>
      <pos A="0.995916" C="0.000978264" G="0.000978264" T="0.00212733"/>
      <pos A="0.126351" C="0.000978264" G="0.000978264" T="0.871693"/>
      <pos A="0.995916" C="0.000978264" G="0.000978264" T="0.00212733"/>
      <pos A="0.995916" C="0.000978264" G="0.000978264" T="0.00212733"/>
      <pos A="0.00212733" C="0.0630901" G="0.000978264" T="0.933804"/>
      <pos A="0.126351" C="0.311537" G="0.497873" T="0.0642391"/>
      <pos A="0.933804" C="0.000978264" G="0.000978264" T="0.0642391"/>
      <pos A="0.00212733" C="0.000978264" G="0.000978264" T="0.995916"/>
      <pos A="0.00212733" C="0.000978264" G="0.125202" T="0.871693"/>
      <pos A="0.561134" C="0.249425" G="0.000978264" T="0.188463"/>
      <pos A="0.00212733" C="0.000978264" G="0.000978264" T="0.995916"/>
      <pos A="0.188463" C="0.808432" G="0.000978264" T="0.00212733"/>
      <pos A="0.995916" C="0.000978264" G="0.000978264" T="0.00212733"/>
      <pos A="0.312686" C="0.0630901" G="0.125202" T="0.499022"/>
      <pos A="0.0642391" C="0.000978264" G="0.0630901" T="0.871693"/>
      <pos A="0.0642391" C="0.000978264" G="0.187314" T="0.747469"/>
      <pos A="0.623245" C="0.000978264" G="0.0630901" T="0.312686"/>
      <pos A="0.188463" C="0.311537" G="0.435761" T="0.0642391"/>
    </motif>
    <motif db="1" id="fur" length="18" nsites="9" evalue="4.0e-012"
        url="http://arep.med.harvard.edu/ecoli_matrices/fur.html">
      <pos A="0.223544" C="0.00173078" G="0.551182" T="0.223544"/>
      <pos A="0.553215" C="0.00173078" G="0.221511" T="0.223544"/>
      <pos A="0.333434" C="0.111621" G="0.00173078" T="0.553215"/>
      <pos A="0.772995" C="0.111621" G="0.00173078" T="0.113654"/>
      <pos A="0.882885" C="0.00173078" G="0.00173078" T="0.113654"/>
      <pos A="0.00376373" C="0.111621" G="0.00173078" T="0.882885"/>
      <pos A="0.00376373" C="0.00173078" G="0.661072" T="0.333434"/>
      <pos A="0.772995" C="0.111621" G="0.111621" T="0.00376373"/>
      <pos A="0.00376373" C="0.00173078" G="0.00173078" T="0.992775"/>
      <pos A="0.443324" C="0.00173078" G="0.00173078" T="0.553215"/>
      <pos A="0.443324" C="0.221511" G="0.221511" T="0.113654"/>
      <pos A="0.00376373" C="0.111621" G="0.221511" T="0.663105"/>
      <pos A="0.00376373" C="0.661072" G="0.111621" T="0.223544"/>
      <pos A="0.882885" C="0.00173078" G="0.111621" T="0.00376373"/>
      <pos A="0.113654" C="0.111621" G="0.00173078" T="0.772995"/>
      <pos A="0.00376373" C="0.00173078" G="0.00173078" T="0.992775"/>
      <pos A="0.223544" C="0.00173078" G="0.00173078" T="0.772995"/>
      <pos A="0.113654" C="0.111621" G="0.331401" T="0.443324"/>
    </motif>
    <motif db="2" id="MX000013" alt="Fur" length="19" nsites="32"
        url="http://prodoric.tu-bs.de/matrix.php?matrix_acc=MX000013">
      <pos A="0.125678" C="0.187407" G="0.623544" T="0.0633723"/>
      <pos A="0.748731" C="0.156254" G="0.0316433" T="0.0633723"/>
      <pos A="0.343746" C="0.125101" G="0.187407" T="0.343746"/>
      <pos A="0.873341" C="0.0316433" G="0.0939486" T="0.00106698"/>
      <pos A="0.748731" C="0.0316433" G="0.000490656" T="0.219136"/>
      <pos A="0.0322196" C="0.156254" G="0.0316433" T="0.779883"/>
      <pos A="0.187983" C="0.0939486" G="0.561238" T="0.15683"/>
      <pos A="0.592967" C="0.280864" G="0.0939486" T="0.0322196"/>
      <pos A="0.187983" C="0.0316433" G="0.187407" T="0.592967"/>
      <pos A="0.468357" C="0.0316433" G="0.0316433" T="0.468357"/>
      <pos A="0.686425" C="0.125101" G="0.062796" T="0.125678"/>
      <pos A="0.00106698" C="0.0316433" G="0.0316433" T="0.935646"/>
      <pos A="0.0633723" C="0.779307" G="0.000490656" T="0.15683"/>
      <pos A="0.842188" C="0.000490656" G="0.0316433" T="0.125678"/>
      <pos A="0.15683" C="0.000490656" G="0.125101" T="0.717578"/>
      <pos A="0.15683" C="0.0316433" G="0.000490656" T="0.811036"/>
      <pos A="0.530662" C="0.312017" G="0.0316433" T="0.125678"/>
      <pos A="0.0945249" C="0.0316433" G="0.280864" T="0.592967"/>
      <pos A="0.15683" C="0.685849" G="0.0316433" T="0.125678"/>
    </motif>
    <motif db="2" id="MX000128" alt="Fur" length="19" nsites="51"
        url="http://prodoric.tu-bs.de/matrix.php?matrix_acc=MX000128">
      <pos A="0.157226" C="0.117725" G="0.548254" T="0.176796"/>
      <pos A="0.529046" C="0.176434" G="0.176434" T="0.118087"/>
      <pos A="0.333351" C="0.117725" G="0.117725" T="0.431199"/>
      <pos A="0.842157" C="0.00030822" G="0.0198778" T="0.137657"/>
      <pos A="0.74431" C="0.00030822" G="0.0590171" T="0.196365"/>
      <pos A="0.0593791" C="0.0981554" G="0.0198778" T="0.822588"/>
      <pos A="0.0985174" C="0.0981554" G="0.665671" T="0.137657"/>
      <pos A="0.822588" C="0.0785857" G="0.0394475" T="0.0593791"/>
      <pos A="0.274643" C="0.0394475" G="0.156864" T="0.529046"/>
      <pos A="0.900866" C="0.00030822" G="0.00030822" T="0.0985174"/>
      <pos A="0.76388" C="0.0394475" G="0.0590171" T="0.137657"/>
      <pos A="0.0593791" C="0.196003" G="0.0590171" T="0.685602"/>
      <pos A="0.215934" C="0.254711" G="0.274281" T="0.255073"/>
      <pos A="0.76388" C="0.0394475" G="0.117725" T="0.0789478"/>
      <pos A="0.0789478" C="0.0394475" G="0.0394475" T="0.842157"/>
      <pos A="0.255073" C="0.0198778" G="0.00030822" T="0.724741"/>
      <pos A="0.607324" C="0.176434" G="0.0394475" T="0.176796"/>
      <pos A="0.0202399" C="0.0785857" G="0.117725" T="0.783449"/>
      <pos A="0.118087" C="0.646101" G="0.0785857" T="0.157226"/>
    </motif>
    <motif db="4" id="Fur_21-4" length="21" nsites="27">
      <pos A="0.148865" C="0.111282" G="0.000581183" T="0.739271"/>
      <pos A="0.259566" C="0.0743818" G="0.627888" T="0.0381642"/>
      <pos A="0.813072" C="0.111282" G="0.0743818" T="0.00126384"/>
      <pos A="0.259566" C="0.000581183" G="0.185083" T="0.55477"/>
      <pos A="0.923773" C="0.000581183" G="0.000581183" T="0.0750645"/>
      <pos A="0.886873" C="0.000581183" G="0.0743818" T="0.0381642"/>
      <pos A="0.00126384" C="0.111282" G="0.000581183" T="0.886873"/>
      <pos A="0.185765" C="0.221983" G="0.295784" T="0.296466"/>
      <pos A="0.62857" C="0.148183" G="0.148183" T="0.0750645"/>
      <pos A="0.0750645" C="0.000581183" G="0.0374815" T="0.886873"/>
      <pos A="0.00126384" C="0.000581183" G="0.000581183" T="0.997574"/>
      <pos A="0.59167" C="0.148183" G="0.000581183" T="0.259566"/>
      <pos A="0.00126384" C="0.0374815" G="0.111282" T="0.849972"/>
      <pos A="0.0750645" C="0.84929" G="0.0743818" T="0.00126384"/>
      <pos A="0.886873" C="0.0374815" G="0.0374815" T="0.0381642"/>
      <pos A="0.0381642" C="0.111282" G="0.000581183" T="0.849972"/>
      <pos A="0.00126384" C="0.0374815" G="0.000581183" T="0.960673"/>
      <pos A="0.480968" C="0.0374815" G="0.0374815" T="0.444068"/>
      <pos A="0.222666" C="0.148183" G="0.258884" T="0.370267"/>
      <pos A="0.407167" C="0.480286" G="0.000581183" T="0.111965"/>
      <pos A="0.849972" C="0.0374815" G="0.111282" T="0.00126384"/>
    </motif>
  </targets>
  <matches>
    <query idx="1">
      <target idx="8" rc="y" off="-2" pv="5.16e-14" ev="3.05e-11" qv="5.94e-11"/>
      <target idx="5" rc="n" off="-2" pv="1.94e-13" ev="1.14e-10" qv="1.12e-10"/>
      <target idx="12" rc="y" off="-1" pv="8.81e-11" ev="5.21e-08" qv="2.13e-08"/>
      <target idx="3" rc="y" off="-1" pv="1.11e-10" ev="6.57e-08" qv="2.13e-08"/>
      <target idx="4" rc="n" off="-5" pv="1.89e-10" ev="1.12e-07" qv="3.12e-08"/>
      <target idx="2" rc="n" off="1" pv="3.26e-09" ev="1.92e-06" qv="3.75e-07"/>
      <target idx="11" rc="n" off="-2" pv="1.39e-08" ev="8.24e-06" qv="1.23e-06"/>
      <target idx="1" rc="n" off="1" pv="5.19e-08" ev="3.07e-05" qv="4.27e-06"/>
      <target idx="7" rc="n" off="-2" pv="1.07e-07" ev="6.33e-05" qv="8.22e-06"/>
      <target idx="6" rc="n" off="-7" pv="1.67e-06" ev="9.88e-04" qv="1.12e-04"/>
      <target idx="10" rc="y" off="-2" pv="6.29e-06" ev="3.72e-03" qv="3.45e-04"/>
      <target idx="0" rc="y" off="17" pv="1.28e-05" ev="7.59e-03" qv="6.72e-04"/>
      <target idx="9" rc="y" off="-3" pv="1.38e-05" ev="8.13e-03" qv="6.89e-04"/>
    </query>
  </matches>
  <runtime cycles="13158068" seconds="13.158"/>
</tomtom>
